flake8_eradicate.py
flake8_eradicate-0.4.0.dist-info/entry_points.txt
flake8_eradicate-0.4.0.dist-info/LICENSE
flake8_eradicate-0.4.0.dist-info/WHEEL
flake8_eradicate-0.4.0.dist-info/METADATA
flake8_eradicate-0.4.0.dist-info/RECORD
