Metadata-Version: 2.1
Name: flake8-eradicate
Version: 0.4.0
Summary: Flake8 plugin to find commented out code
Home-page: https://github.com/sobolevn/flake8-eradicate
License: MIT
Keywords: flake8,plugin,linting,wemake.services,code quality
Author: Nikita Sobolev
Author-email: mail@sobolevn.me
Requires-Python: >=3.5,<4.0
Classifier: Development Status :: 4 - Beta
Classifier: Environment :: Console
Classifier: Framework :: Flake8
Classifier: Intended Audience :: Developers
Classifier: License :: OSI Approved :: MIT License
Classifier: Operating System :: OS Independent
Classifier: Programming Language :: Python :: 3
Classifier: Programming Language :: Python :: 3.5
Classifier: Programming Language :: Python :: 3.6
Classifier: Programming Language :: Python :: 3.7
Classifier: Programming Language :: Python :: 3.8
Classifier: Topic :: Software Development :: Libraries :: Python Modules
Classifier: Topic :: Software Development :: Quality Assurance
Requires-Dist: attrs
Requires-Dist: eradicate (>=1.0,<2.0)
Requires-Dist: flake8 (>=3.5,<4.0)
Project-URL: Repository, https://github.com/sobolevn/flake8-eradicate
